LICENSE
MANIFEST.in
README.md
setup.cfg
setup.py
django_react_toolkit/__init__.py
django_react_toolkit/apps.py
django_react_toolkit/conf.py
django_react_toolkit/proxy.py
django_react_toolkit/urls.py
django_react_toolkit/views.py
django_react_toolkit.egg-info/PKG-INFO
django_react_toolkit.egg-info/SOURCES.txt
django_react_toolkit.egg-info/dependency_links.txt
django_react_toolkit.egg-info/requires.txt
django_react_toolkit.egg-info/top_level.txt
django_react_toolkit/management/__init__.py
django_react_toolkit/management/commands/__init__.py
django_react_toolkit/management/commands/runtkserver.py